VNP09GA_002/VNP09GA_002.py
VNP09GA_002/VNP09GA_granule.py
VNP09GA_002/__init__.py
VNP09GA_002/available_dates.py
VNP09GA_002/connection.py
VNP09GA_002/constants.py
VNP09GA_002/retrieve_granule.py
VNP09GA_002/search_granules.py
VNP09GA_002/version.txt
vnp09ga_002-1.2.1.dist-info/licenses/LICENSE
vnp09ga_002-1.2.1.dist-info/METADATA
vnp09ga_002-1.2.1.dist-info/WHEEL
vnp09ga_002-1.2.1.dist-info/top_level.txt
vnp09ga_002-1.2.1.dist-info/RECORD
