Metadata-Version: 2.4
Name: VNP09GA-002
Version: 1.2.1
Summary: VIIRS/NPP Surface Reflectance Daily L2G Global 1 km and 500 m SIN Grid Search and Download Utility
Author-email: "Gregory H. Halverson" <gregory.h.halverson@jpl.nasa.gov>
Project-URL: Homepage, https://github.com/STARS-Data-Fusion/VNP09GA-002
Classifier: Programming Language :: Python :: 3
Classifier: Operating System :: OS Independent
Requires-Python: >=3.10
License-File: LICENSE
Requires-Dist: colored-logging
Requires-Dist: earthaccess
Requires-Dist: modland>=1.1.0
Requires-Dist: python-dateutil
Requires-Dist: rasters
Requires-Dist: sentinel-tiles
Requires-Dist: VIIRS-Tiled-Granules>=1.0.2
Provides-Extra: dev
Requires-Dist: build; extra == "dev"
Requires-Dist: pytest>=6.0; extra == "dev"
Requires-Dist: pytest-cov; extra == "dev"
Requires-Dist: jupyter; extra == "dev"
Requires-Dist: pytest; extra == "dev"
Requires-Dist: twine; extra == "dev"
Dynamic: license-file
